{
  "$schema": "https://developer.microsoft.com/json-schemas/fabric/item/report/definition/visualContainer/2.5.0/schema.json",
  "name": "dc323bfbee63a34ac86b",
  "position": {
    "x": 1004.1988950276243,
    "y": 690.828729281768,
    "z": 6000,
    "height": 29.171270718232044,
    "width": 275.8011049723757,
    "tabOrder": 5000
  },
  "visual": {
    "visualType": "card",
    "query": {
      "queryState": {
        "Values": {
          "projections": [
            {
              "field": {
                "Measure": {
                  "Expression": {
                    "SourceRef": {
                      "Entity": "KeyMeasures"
                    }
                  },
                  "Property": "page_two_title"
                }
              },
              "queryRef": "KeyMeasures.page_two_title",
              "nativeQueryRef": "page_two_title"
            }
          ]
        }
      }
    },
    "objects": {
      "categoryLabels": [
        {
          "properties": {
            "show": {
              "expr": {
                "Literal": {
                  "Value": "false"
                }
              }
            }
          }
        }
      ],
      "labels": [
        {
          "properties": {
            "fontSize": {
              "expr": {
                "Literal": {
                  "Value": "10D"
                }
              }
            }
          }
        }
      ]
    },
    "drillFilterOtherVisuals": true
  }
}