{
  "$schema": "https://developer.microsoft.com/json-schemas/fabric/item/report/definition/visualContainer/2.5.0/schema.json",
  "name": "b7be43e1b9dba8d440b0",
  "position": {
    "x": 0,
    "y": 438,
    "z": 0,
    "height": 258,
    "width": 430,
    "tabOrder": 0
  },
  "visual": {
    "visualType": "textbox",
    "objects": {
      "general": [
        {
          "properties": {
            "paragraphs": [
              {
                "textRuns": [
                  {
                    "value": "≥"
                  }
                ]
              }
            ]
          }
        }
      ]
    },
    "drillFilterOtherVisuals": true
  }
}