{
  "version": "1.1.0",
  "diagrams": [
    {
      "ordinal": 0,
      "scrollPosition": {
        "x": 176.55780595966104,
        "y": 372.828376662391
      },
      "nodes": [
        {
          "location": {
            "x": 0,
            "y": 0
          },
          "nodeIndex": "Calendar",
          "size": {
            "height": 104,
            "width": 234
          },
          "zIndex": 10,
          "expandedHeight": 296
        },
        {
          "location": {
            "x": 295.82268492845736,
            "y": 196.66677378451351
          },
          "nodeIndex": "DIM COUNTRY",
          "nodeLineageTag": "040ee51b-e479-4456-b9de-32547dde189f",
          "size": {
            "height": 104,
            "width": 234
          },
          "zIndex": 4,
          "expandedHeight": 104
        },
        {
          "location": {
            "x": 955.41899325762085,
            "y": 0
          },
          "nodeIndex": "DIM_AGE",
          "nodeLineageTag": "bbda7cb2-f964-4241-817d-d7bd147de2cf",
          "size": {
            "height": 104,
            "width": 234
          },
          "zIndex": 5,
          "expandedHeight": 176
        },
        {
          "location": {
            "x": 2034.1802184409448,
            "y": 0
          },
          "nodeIndex": "DIM_BODY_REGION",
          "nodeLineageTag": "5313bb13-59b4-48da-943d-9455fa00df4c",
          "size": {
            "height": 104,
            "width": 234
          },
          "zIndex": 6,
          "expandedHeight": 104
        },
        {
          "location": {
            "x": 2243.9959234327625,
            "y": 309.95264225376718
          },
          "nodeIndex": "DIM_DISCHAGRE",
          "nodeLineageTag": "1433fcf5-b67e-478d-ba83-2ff01f5845f8",
          "size": {
            "height": 104,
            "width": 234
          },
          "zIndex": 16,
          "expandedHeight": 152
        },
        {
          "location": {
            "x": 1626.1806742293807,
            "y": 186.38383800503493
          },
          "nodeIndex": "DIM_GENDER",
          "nodeLineageTag": "0ae4c4ec-3eaf-4226-9740-0cd8db420aa6",
          "size": {
            "height": 104,
            "width": 234
          },
          "zIndex": 18,
          "expandedHeight": 128
        },
        {
          "location": {
            "x": 1755.3396986804041,
            "y": 0
          },
          "nodeIndex": "DIM_INJURY_ACTIVITY",
          "nodeLineageTag": "03b4465e-269e-415b-8b44-fb51a722c7b1",
          "size": {
            "height": 104,
            "width": 234
          },
          "zIndex": 17,
          "expandedHeight": 152
        },
        {
          "location": {
            "x": 1318.0345825356044,
            "y": 156.08880708749143
          },
          "nodeIndex": "DIM_INJURY_CAUSE",
          "nodeLineageTag": "3c833ef7-1be0-48bb-86e0-9c202ea3e667",
          "size": {
            "height": 248,
            "width": 234
          },
          "zIndex": 13
        },
        {
          "location": {
            "x": 1888.25148267485,
            "y": 398.62439342117312
          },
          "nodeIndex": "DIM_INJURY_INTENT",
          "nodeLineageTag": "69d4d3af-b501-4e3a-a876-d8f10f24cf70",
          "size": {
            "height": 104,
            "width": 234
          },
          "zIndex": 7,
          "expandedHeight": 128
        },
        {
          "location": {
            "x": 2033.0446357386716,
            "y": 141.13458253560498
          },
          "nodeIndex": "DIM_INJURY_PLACE",
          "nodeLineageTag": "f197a711-df9f-43c5-ad6a-af9d56b84b20",
          "size": {
            "height": 104,
            "width": 234
          },
          "zIndex": 12,
          "expandedHeight": 152
        },
        {
          "location": {
            "x": 1472.0703261797021,
            "y": 462.68025943351353
          },
          "nodeIndex": "DIM_INJURY_SEVERITY",
          "nodeLineageTag": "1f6c12fa-165b-4ef6-a8d6-73305f39ba70",
          "size": {
            "height": 104,
            "width": 234
          },
          "zIndex": 11,
          "expandedHeight": 128
        },
        {
          "location": {
            "x": 658.8564716560511,
            "y": 0
          },
          "nodeIndex": "DIM_INJURY_TYPE",
          "nodeLineageTag": "ec7427fe-baac-40b0-ac83-0ee93cb2b448",
          "size": {
            "height": 104,
            "width": 234
          },
          "zIndex": 19,
          "expandedHeight": 128
        },
        {
          "location": {
            "x": 1488.2291159565398,
            "y": 0
          },
          "nodeIndex": "DIM_TRANSPORT",
          "nodeLineageTag": "e544d893-de04-4208-ac71-3465cb51df4b",
          "size": {
            "height": 104,
            "width": 234
          },
          "zIndex": 8,
          "expandedHeight": 128
        },
        {
          "location": {
            "x": 369.81295387979515,
            "y": 660.63231031097769
          },
          "nodeIndex": "FACT_ATR",
          "nodeLineageTag": "cf5fb583-fad1-460b-bba1-284a8ef1dcc4",
          "size": {
            "height": 847.98808751088791,
            "width": 416
          },
          "zIndex": 14
        },
        {
          "location": {
            "x": 0,
            "y": 464.27658963974767
          },
          "nodeIndex": "RESTRICTED_HOSPITAL",
          "nodeLineageTag": "69b05caa-ae27-4cd9-9d6b-b0eca080af72",
          "size": {
            "height": 104,
            "width": 234
          },
          "zIndex": 15,
          "expandedHeight": 152
        },
        {
          "location": {
            "x": 0,
            "y": 241.72910238792105
          },
          "nodeIndex": "KeyMeasures",
          "size": {
            "height": 72,
            "width": 234
          },
          "zIndex": 9,
          "expandedHeight": 104
        },
        {
          "location": {
            "x": 762.14794083159472,
            "y": 346.90688186627597
          },
          "nodeIndex": "Time intelligence",
          "nodeLineageTag": "d5768129-e9a7-4d78-8368-cb9590915c2d",
          "size": {
            "height": 72,
            "width": 234
          },
          "zIndex": 3,
          "expandedHeight": 128
        },
        {
          "location": {
            "x": 369.814295612022,
            "y": 0
          },
          "nodeIndex": "DIM_STATE",
          "size": {
            "height": 104,
            "width": 234
          },
          "zIndex": 1,
          "expandedHeight": 272
        },
        {
          "location": {
            "x": 737.131224233472,
            "y": 463.81499729580867
          },
          "nodeIndex": "DIM_ICD_ALL_CODES",
          "nodeLineageTag": "3c77e549-b962-42af-a729-5391ded9986c",
          "size": {
            "height": 152,
            "width": 234
          },
          "zIndex": 0
        }
      ],
      "name": "All tables",
      "zoomValue": 116.67566827776834,
      "pinKeyFieldsToTop": false,
      "showExtraHeaderInfo": false,
      "hideKeyFieldsWhenCollapsed": false,
      "tablesLocked": false
    },
    {
      "ordinal": 1,
      "scrollPosition": {
        "x": 0,
        "y": 0
      },
      "nodes": [
        {
          "location": {
            "x": 1045.0107481669509,
            "y": 395.97711201899585
          },
          "nodeIndex": "FACT_ATR",
          "nodeLineageTag": "cf5fb583-fad1-460b-bba1-284a8ef1dcc4",
          "size": {
            "height": 696.829664,
            "width": 320
          },
          "zIndex": 16
        },
        {
          "location": {
            "x": 1317.5061313882597,
            "y": 0
          },
          "nodeIndex": "DIM_INJURY_CAUSE",
          "nodeLineageTag": "3c833ef7-1be0-48bb-86e0-9c202ea3e667",
          "size": {
            "height": 104,
            "width": 234
          },
          "zIndex": 1,
          "expandedHeight": 300
        },
        {
          "location": {
            "x": 742.5132187740262,
            "y": 0
          },
          "nodeIndex": "DIM COUNTRY",
          "nodeLineageTag": "040ee51b-e479-4456-b9de-32547dde189f",
          "size": {
            "height": 104,
            "width": 234
          },
          "zIndex": 2,
          "expandedHeight": 104
        },
        {
          "location": {
            "x": 475.7763503008191,
            "y": 0
          },
          "nodeIndex": "DIM_DISCHAGRE",
          "nodeLineageTag": "1433fcf5-b67e-478d-ba83-2ff01f5845f8",
          "size": {
            "height": 152,
            "width": 226
          },
          "zIndex": 3
        },
        {
          "location": {
            "x": 2180.8400901165037,
            "y": 0
          },
          "nodeIndex": "DIM_INJURY_ACTIVITY",
          "nodeLineageTag": "03b4465e-269e-415b-8b44-fb51a722c7b1",
          "size": {
            "height": 152,
            "width": 234
          },
          "zIndex": 4
        },
        {
          "location": {
            "x": 0,
            "y": 0
          },
          "nodeIndex": "Calendar",
          "nodeLineageTag": "0eacafb2-20e6-4e5d-bc6a-0795aaaa3553",
          "size": {
            "height": 104,
            "width": 234
          },
          "zIndex": 5,
          "expandedHeight": 300
        },
        {
          "location": {
            "x": 1196.5663709357684,
            "y": 161.30070494575216
          },
          "nodeIndex": "DIM_INJURY_INTENT",
          "nodeLineageTag": "69d4d3af-b501-4e3a-a876-d8f10f24cf70",
          "size": {
            "height": 104,
            "width": 234
          },
          "zIndex": 6,
          "expandedHeight": 128
        },
        {
          "location": {
            "x": 1900.4877712122131,
            "y": 0
          },
          "nodeIndex": "DIM_INJURY_TYPE",
          "nodeLineageTag": "ec7427fe-baac-40b0-ac83-0ee93cb2b448",
          "size": {
            "height": 104,
            "width": 234
          },
          "zIndex": 7,
          "expandedHeight": 128
        },
        {
          "location": {
            "x": 1582.2905816712678,
            "y": 0
          },
          "nodeIndex": "DIM_INJURY_SEVERITY",
          "nodeLineageTag": "1f6c12fa-165b-4ef6-a8d6-73305f39ba70",
          "size": {
            "height": 104,
            "width": 234
          },
          "zIndex": 8,
          "expandedHeight": 152
        },
        {
          "location": {
            "x": 2005.3266296836705,
            "y": 153.10191984859466
          },
          "nodeIndex": "DIM_AGE",
          "nodeLineageTag": "bbda7cb2-f964-4241-817d-d7bd147de2cf",
          "size": {
            "height": 248,
            "width": 234
          },
          "zIndex": 15
        },
        {
          "location": {
            "x": 897.7744429504603,
            "y": 161.64074377708039
          },
          "nodeIndex": "DIM_GENDER",
          "nodeLineageTag": "0ae4c4ec-3eaf-4226-9740-0cd8db420aa6",
          "size": {
            "height": 104,
            "width": 234
          },
          "zIndex": 9,
          "expandedHeight": 128
        },
        {
          "location": {
            "x": 1726.2670733639068,
            "y": 159.19350594448724
          },
          "nodeIndex": "DIM_TRANSPORT",
          "nodeLineageTag": "e544d893-de04-4208-ac71-3465cb51df4b",
          "size": {
            "height": 104,
            "width": 234
          },
          "zIndex": 10,
          "expandedHeight": 128
        },
        {
          "location": {
            "x": 610.839306335535,
            "y": 165.42129945911665
          },
          "nodeIndex": "DIM_INJURY_PLACE",
          "nodeLineageTag": "f197a711-df9f-43c5-ad6a-af9d56b84b20",
          "size": {
            "height": 104,
            "width": 234
          },
          "zIndex": 11,
          "expandedHeight": 176
        },
        {
          "location": {
            "x": 1447.8199637115847,
            "y": 163.68530351637511
          },
          "nodeIndex": "DIM_BODY_REGION",
          "nodeLineageTag": "5313bb13-59b4-48da-943d-9455fa00df4c",
          "size": {
            "height": 104,
            "width": 234
          },
          "zIndex": 14,
          "expandedHeight": 176
        },
        {
          "location": {
            "x": 336,
            "y": 156.7478279625027
          },
          "nodeIndex": "RESTRICTED_HOSPITAL",
          "nodeLineageTag": "69b05caa-ae27-4cd9-9d6b-b0eca080af72",
          "size": {
            "height": 104,
            "width": 234
          },
          "zIndex": 12,
          "expandedHeight": 272
        },
        {
          "location": {
            "x": 2485.7130466192989,
            "y": 0
          },
          "nodeIndex": "DIM_STATE",
          "size": {
            "height": 300,
            "width": 234
          },
          "zIndex": 0
        }
      ],
      "name": "FACT_ATR",
      "zoomValue": 40.05255472488313,
      "pinKeyFieldsToTop": true,
      "showExtraHeaderInfo": false,
      "hideKeyFieldsWhenCollapsed": false,
      "tablesLocked": false
    },
    {
      "ordinal": 2,
      "scrollPosition": {
        "x": 0,
        "y": 0
      },
      "nodes": [
        {
          "location": {
            "x": 431.10134664360805,
            "y": 128.00749963575936
          },
          "nodeIndex": "DIM_GENDER",
          "nodeLineageTag": "0ae4c4ec-3eaf-4226-9740-0cd8db420aa6",
          "size": {
            "height": 104,
            "width": 234
          },
          "zIndex": 9,
          "expandedHeight": 128
        },
        {
          "location": {
            "x": 711.86341433348753,
            "y": 123.63802400724558
          },
          "nodeIndex": "DIM COUNTRY",
          "nodeLineageTag": "040ee51b-e479-4456-b9de-32547dde189f",
          "size": {
            "height": 104,
            "width": 234
          },
          "zIndex": 8,
          "expandedHeight": 104
        },
        {
          "location": {
            "x": 1116.7785167021693,
            "y": 0
          },
          "nodeIndex": "DIM_INJURY_CAUSE",
          "nodeLineageTag": "3c833ef7-1be0-48bb-86e0-9c202ea3e667",
          "size": {
            "height": 104,
            "width": 234
          },
          "zIndex": 15,
          "expandedHeight": 300
        },
        {
          "location": {
            "x": 1838.0319249093991,
            "y": 124.03815286778331
          },
          "nodeIndex": "DIM_BODY_REGION",
          "nodeLineageTag": "5313bb13-59b4-48da-943d-9455fa00df4c",
          "size": {
            "height": 104,
            "width": 234
          },
          "zIndex": 3,
          "expandedHeight": 176
        },
        {
          "location": {
            "x": 1956.7963170442381,
            "y": 0
          },
          "nodeIndex": "DIM_INJURY_SEVERITY",
          "nodeLineageTag": "1f6c12fa-165b-4ef6-a8d6-73305f39ba70",
          "size": {
            "height": 104,
            "width": 234
          },
          "zIndex": 4,
          "expandedHeight": 152
        },
        {
          "location": {
            "x": 1562.5499739503769,
            "y": 126.71924315991146
          },
          "nodeIndex": "DIM_INJURY_PLACE",
          "nodeLineageTag": "f197a711-df9f-43c5-ad6a-af9d56b84b20",
          "size": {
            "height": 104,
            "width": 234
          },
          "zIndex": 5,
          "expandedHeight": 176
        },
        {
          "location": {
            "x": 307.226317788251,
            "y": 0
          },
          "nodeIndex": "DIM_DISCHAGRE",
          "nodeLineageTag": "1433fcf5-b67e-478d-ba83-2ff01f5845f8",
          "size": {
            "height": 104,
            "width": 234
          },
          "zIndex": 12,
          "expandedHeight": 152
        },
        {
          "location": {
            "x": 991.8234213801054,
            "y": 124.93266317841699
          },
          "nodeIndex": "DIM_INJURY_ACTIVITY",
          "nodeLineageTag": "03b4465e-269e-415b-8b44-fb51a722c7b1",
          "size": {
            "height": 104,
            "width": 234
          },
          "zIndex": 6,
          "expandedHeight": 152
        },
        {
          "location": {
            "x": 1680.8252433714856,
            "y": 0
          },
          "nodeIndex": "DIM_INJURY_INTENT",
          "nodeLineageTag": "69d4d3af-b501-4e3a-a876-d8f10f24cf70",
          "size": {
            "height": 104,
            "width": 234
          },
          "zIndex": 13,
          "expandedHeight": 128
        },
        {
          "location": {
            "x": 1386.3256471267682,
            "y": 0
          },
          "nodeIndex": "DIM_TRANSPORT",
          "nodeLineageTag": "e544d893-de04-4208-ac71-3465cb51df4b",
          "size": {
            "height": 104,
            "width": 234
          },
          "zIndex": 14,
          "expandedHeight": 128
        },
        {
          "location": {
            "x": 575.87060652061678,
            "y": 0
          },
          "nodeIndex": "DIM_AGE",
          "nodeLineageTag": "bbda7cb2-f964-4241-817d-d7bd147de2cf",
          "size": {
            "height": 104,
            "width": 234
          },
          "zIndex": 10,
          "expandedHeight": 248
        },
        {
          "location": {
            "x": 841.92853177432573,
            "y": 0
          },
          "nodeIndex": "DIM_INJURY_TYPE",
          "nodeLineageTag": "ec7427fe-baac-40b0-ac83-0ee93cb2b448",
          "size": {
            "height": 104,
            "width": 234
          },
          "zIndex": 11,
          "expandedHeight": 128
        },
        {
          "location": {
            "x": 0,
            "y": 0
          },
          "nodeIndex": "Calendar",
          "nodeLineageTag": "0eacafb2-20e6-4e5d-bc6a-0795aaaa3553",
          "size": {
            "height": 104,
            "width": 234
          },
          "zIndex": 7,
          "expandedHeight": 300
        },
        {
          "location": {
            "x": 1279.3982616038193,
            "y": 124.6112009712449
          },
          "nodeIndex": "DIM_STATE",
          "size": {
            "height": 104,
            "width": 234
          },
          "zIndex": 0,
          "expandedHeight": 300
        }
      ],
      "name": "FACT_NATIONAL",
      "zoomValue": 65.122777764195916,
      "pinKeyFieldsToTop": false,
      "showExtraHeaderInfo": false,
      "hideKeyFieldsWhenCollapsed": false,
      "tablesLocked": false
    }
  ],
  "selectedDiagram": "All tables",
  "defaultDiagram": "All tables"
}